nonebot_plugin_alist/__init__.py
nonebot_plugin_alist/config.py
nonebot_plugin_alist/dependency.py
nonebot_plugin_alist/models.py
nonebot_plugin_alist/request.py
nonebot_plugin_alist/api/auth.py
nonebot_plugin_alist/api/fs.py
nonebot_plugin_alist/api/admin/task.py
nonebot_plugin_alist/cmd/__init__.py
nonebot_plugin_alist/cmd/alist_commands.py
nonebot_plugin_alist/cmd/account/__init__.py
nonebot_plugin_alist/cmd/account/on_account_add.py
nonebot_plugin_alist/cmd/account/on_account_del.py
nonebot_plugin_alist/cmd/account/on_account_info.py
nonebot_plugin_alist/cmd/account/on_account_list.py
nonebot_plugin_alist/cmd/account/on_account_switch.py
nonebot_plugin_alist/cmd/account/on_logout.py
nonebot_plugin_alist/cmd/account/on_me.py
nonebot_plugin_alist/cmd/account/on_relogin.py
nonebot_plugin_alist/cmd/alist/__init__.py
nonebot_plugin_alist/cmd/alist/on_help.py
nonebot_plugin_alist/cmd/download/__init__.py
nonebot_plugin_alist/cmd/download/on_download_add.py
nonebot_plugin_alist/cmd/download/on_download_cancel.py
nonebot_plugin_alist/cmd/download/on_download_list.py
nonebot_plugin_alist/cmd/download/on_download_policy.py
nonebot_plugin_alist/cmd/download/on_download_tool.py
nonebot_plugin_alist/cmd/fs/__init__.py
nonebot_plugin_alist/cmd/fs/on_cd.py
nonebot_plugin_alist/cmd/fs/on_ls.py
nonebot_plugin_alist/cmd/fs/on_pwd.py
nonebot_plugin_alist/common/download_option_service.py
nonebot_plugin_alist/common/auth_service/login_service.py
nonebot_plugin_alist/common/auth_service/logout_service.py
nonebot_plugin_alist/context/alist_user.py
nonebot_plugin_alist/enum/offline_download.py
nonebot_plugin_alist/exception/alist_plugin_exception.py
nonebot_plugin_alist/exception/auth_exception.py
nonebot_plugin_alist/hook/__init__.py
nonebot_plugin_alist/hook/tortoise.py
nonebot_plugin_alist/message/account.py
nonebot_plugin_alist/message/fs.py
nonebot_plugin_alist/message/task.py
nonebot_plugin_alist-1.1.1.dist-info/LICENSE
nonebot_plugin_alist-1.1.1.dist-info/METADATA
nonebot_plugin_alist-1.1.1.dist-info/WHEEL
nonebot_plugin_alist-1.1.1.dist-info/top_level.txt
nonebot_plugin_alist-1.1.1.dist-info/RECORD
