Metadata-Version: 2.1
Name: nonebot-plugin-alist
Version: 1.1.1
Summary: 一个支持Alist多账号管理的NoneBot插件
Author-email: iam57 <me@iam57.com>
License: MIT
Requires-Python: <3.13,>=3.11
License-File: LICENSE
Requires-Dist: nonebot2>=2.3.2
Requires-Dist: nonebot-adapter-onebot>=2.4.4
Requires-Dist: httpx>=0.27.0
Requires-Dist: tortoise-orm[aiosqlite]>=0.21.5
Requires-Dist: aiosqlite>=0.17.0
Requires-Dist: nonebot-plugin-alconna>=0.51.1
Requires-Dist: ruff>=0.5.7
